pydiatr/__init__.py
pydiatr/handler.py
pydiatr/registry.py
pydiatr-0.1.0.dist-info/LICENSE
pydiatr-0.1.0.dist-info/METADATA
pydiatr-0.1.0.dist-info/WHEEL
pydiatr-0.1.0.dist-info/RECORD
