Metadata-Version: 2.1
Name: pydiatr
Version: 0.1.0
Summary: 
Author: gage russell
Requires-Python: >=3.9,<3.12
Classifier: Programming Language :: Python :: 3
Classifier: Programming Language :: Python :: 3.9
Classifier: Programming Language :: Python :: 3.10
Classifier: Programming Language :: Python :: 3.11
Requires-Dist: pydantic (>=2.9.2,<3.0.0)
